pdrtpy/__init__.py
pdrtpy/measurement.py
pdrtpy/modelset.py
pdrtpy/pdrutils.py
pdrtpy/models/kosmatau/versionX/z=1/models.tab
pdrtpy/models/kosmatau/versionX/z=1/oicpweb.kosmatau.fits
pdrtpy/models/wolfirekaufman/version2006/constant_density/smc/ciioifirwebsmc.fits
pdrtpy/models/wolfirekaufman/version2006/constant_density/smc/ciioifirwebsmccut.fits
pdrtpy/models/wolfirekaufman/version2006/constant_density/smc/cpsmcweb.fits
pdrtpy/models/wolfirekaufman/version2006/constant_density/smc/firsmcweb.fits
pdrtpy/models/wolfirekaufman/version2006/constant_density/smc/models.tab
pdrtpy/models/wolfirekaufman/version2006/constant_density/smc/oicpsmcweb.fits
pdrtpy/models/wolfirekaufman/version2006/constant_density/smc/oicpsmcwebcut.fits
pdrtpy/models/wolfirekaufman/version2006/constant_density/smc/oicpwebsmc.fits
pdrtpy/models/wolfirekaufman/version2006/constant_density/z=1/CII158_CO32.fits
pdrtpy/models/wolfirekaufman/version2006/constant_density/z=1/CII158_CO65.fits
pdrtpy/models/wolfirekaufman/version2006/constant_density/z=1/CII158_FIR.fits
pdrtpy/models/wolfirekaufman/version2006/constant_density/z=1/CO65_CO32.fits
pdrtpy/models/wolfirekaufman/version2006/constant_density/z=1/FEII1p60_FEII1p64.fits
pdrtpy/models/wolfirekaufman/version2006/constant_density/z=1/FEII1p64_FEII5p34.fits
pdrtpy/models/wolfirekaufman/version2006/constant_density/z=1/ci609firweb.fits
pdrtpy/models/wolfirekaufman/version2006/constant_density/z=1/ciciweb.fits
pdrtpy/models/wolfirekaufman/version2006/constant_density/z=1/cico21web.fits
pdrtpy/models/wolfirekaufman/version2006/constant_density/z=1/cico32web.fits
pdrtpy/models/wolfirekaufman/version2006/constant_density/z=1/cico43web.fits
pdrtpy/models/wolfirekaufman/version2006/constant_density/z=1/cico54web.fits
pdrtpy/models/wolfirekaufman/version2006/constant_density/z=1/cico65web.fits
pdrtpy/models/wolfirekaufman/version2006/constant_density/z=1/cicoweb.fits
pdrtpy/models/wolfirekaufman/version2006/constant_density/z=1/ciici609web.fits
pdrtpy-2.1.1.dist-info/LICENSE
pdrtpy-2.1.1.dist-info/METADATA
pdrtpy-2.1.1.dist-info/WHEEL
pdrtpy-2.1.1.dist-info/top_level.txt
pdrtpy-2.1.1.dist-info/RECORD
