Metadata-Version: 2.1
Name: pdrtpy
Version: 2.1.1
Summary: PhotoDissociation Region Toolbox (PDRT), astrophysics analysis tools
Home-page: http://dustem.astro.umd.edu
Author: Marc W. Pound, Mark G. Wolfire
Author-email: mpound@umd.edu
License: GPLv3
Project-URL: Documentation, https://pdrtpy.readthedocs.io
Project-URL: Source Code, https://github.com/mpound/pdrtpy
Keywords: PDR photodissociation astronomy astrophysics
Platform: UNKNOWN
Classifier: Development Status :: 5 - Production/Stable
Classifier: Programming Language :: Python :: 3
Classifier: License :: OSI Approved :: GNU General Public License v3 (GPLv3)
Classifier: Topic :: Scientific/Engineering :: Astronomy
Classifier: Intended Audience :: Science/Research
Requires-Python: >=3.7
Requires-Dist: astropy
Requires-Dist: numpy
Requires-Dist: scipy
Requires-Dist: matplotlib
Requires-Dist: lmfit
Requires-Dist: numdifftools
